my_math/__init__.py
my_math/operations.py
mahesh_mymath-0.1.dist-info/METADATA
mahesh_mymath-0.1.dist-info/WHEEL
mahesh_mymath-0.1.dist-info/top_level.txt
mahesh_mymath-0.1.dist-info/RECORD
